CHANGES.txt
CONTRIBUTORS.txt
LICENSE
MANIFEST.in
README.md
setup.cfg
setup.py
sidecar/__init__.py
sidecar.endpoint.egg-info/PKG-INFO
sidecar.endpoint.egg-info/SOURCES.txt
sidecar.endpoint.egg-info/dependency_links.txt
sidecar.endpoint.egg-info/entry_points.txt
sidecar.endpoint.egg-info/namespace_packages.txt
sidecar.endpoint.egg-info/not-zip-safe
sidecar.endpoint.egg-info/paster_plugins.txt
sidecar.endpoint.egg-info/requires.txt
sidecar.endpoint.egg-info/top_level.txt
sidecar/endpoint/README.txt
sidecar/endpoint/__init__.py
sidecar/endpoint/config.py
sidecar/endpoint/configure.zcml
sidecar/endpoint/browser/__init__.py
sidecar/endpoint/browser/configure.zcml
sidecar/endpoint/browser/endpoint.pt
sidecar/endpoint/browser/view.py
sidecar/endpoint/content/__init__.py
sidecar/endpoint/content/configure.zcml
sidecar/endpoint/interfaces/__init__.py
sidecar/endpoint/portlets/__init__.py
sidecar/endpoint/portlets/configure.zcml
sidecar/endpoint/profiles/default/factorytool.xml
sidecar/endpoint/profiles/default/metadata.xml
sidecar/endpoint/profiles/default/portlets.xml
sidecar/endpoint/profiles/default/types.xml
sidecar/endpoint/tests/__init__.py
sidecar/endpoint/tests/base.py
sidecar/endpoint/tests/test_doctest.py