Metadata-Version: 2.1
Name: sidecar.endpoint
Version: 0.1.1
Summary: UNKNOWN
Home-page: https://github.com/rmontenegroo/sidecar.endpoint
Author: Rodrigo Montenegro de Oliveira
Author-email: montenegro.r@gmail.com
License: Apache v2
Keywords: kubernetes,container,endpoint,discovery
Platform: Linux
Classifier: Programming Language :: Python
Classifier: Programming Language :: Python :: 2.7
Classifier: Framework :: Plone
Classifier: Framework :: Plone :: 4.3
Classifier: Intended Audience :: Developers
Classifier: License :: OSI Approved :: Apache Software License
Requires-Python: >=2.7, <3
Provides-Extra: tests
